trainer/__init__.py
trainer/lib/JsonClass.py
trainer/lib/__init__.py
trainer/lib/demo_dataset.py
trainer/lib/enums.py
trainer/lib/import_utils.py
trainer/lib/misc.py
trainer/lib/tgui/TClassSelector.py
trainer/lib/tgui/TConsole.py
trainer/lib/tgui/TSegTool.py
trainer/lib/tgui/TWindow.py
trainer/lib/tgui/__init__.py
trainer/ml/__init__.py
trainer/ml/augmentation.py
trainer/ml/data_loading.py
trainer/ml/data_model.py
trainer/ml/losses.py
trainer/ml/metrics.py
trainer/ml/predictor.py
trainer/ml/seg_network.py
trainer/ml/torch_utils.py
trainer/ml/utils.py
trainer/ml/visualization.py
trainer/server/__init__.py
trainer/tools/AnnotationGui.py
trainer/tools/__init__.py
trainer/tools/cli.py
tutorials/Network Robustness.py
tutorials/__init__.py
tutorials/model_training.py
tutorials/multi dataloader.py
tutorials/usage_example.py
ai_trainer-0.0.10.dist-info/LICENSE
ai_trainer-0.0.10.dist-info/METADATA
ai_trainer-0.0.10.dist-info/WHEEL
ai_trainer-0.0.10.dist-info/entry_points.txt
ai_trainer-0.0.10.dist-info/top_level.txt
ai_trainer-0.0.10.dist-info/RECORD
