Metadata-Version: 2.1
Name: ai-trainer
Version: 0.0.10
Summary: AI Trainer
Home-page: https://github.com/Telcrome/ai-trainer
Author: Raphael Schaefer
Author-email: raphaelschaefer1@outlook.com
License: UNKNOWN
Download-URL: https://github.com/Telcrome/ai-trainer/archive/0.0.3.tar.gz
Platform: UNKNOWN
Classifier: Programming Language :: Python :: 3
Classifier: License :: OSI Approved :: MIT License
Classifier: Operating System :: OS Independent
Requires-Python: >=3.7
Requires-Dist: numpy
Requires-Dist: opencv-python
Requires-Dist: pydicom
Requires-Dist: PySimpleGui
Requires-Dist: tensorflow
